package_name/__init__.py
package_name/_example.py
our_package_name-1.0.0.dist-info/LICENSE
our_package_name-1.0.0.dist-info/METADATA
our_package_name-1.0.0.dist-info/WHEEL
our_package_name-1.0.0.dist-info/top_level.txt
our_package_name-1.0.0.dist-info/RECORD
