Metadata-Version: 2.1
Name: our_package_name
Version: 1.0.0
Summary: A package to plot interactive dynamic models for Code/Astro 2024
Author-email: "Garcia-Cifuentes, K." <stivengarcia7113@gmail.com>, Bretton <Bretton@example.com>, Elizabeth <Elizabeth@example.com>, Alcatraz <Alcatraz@example.com>, Dionysis <Dionysis@example.com>
Maintainer-email: Keneth Garcia <stivengarcia7113@gmail.com>
License: MIT License
Project-URL: homepage, https://github.com/brettonsimpson/group-13
Project-URL: documentation, https://github.com/brettonsimpson/group-13/tree/Keneth_updates/docs
Keywords: Galactic Dynamics,Rotation Curves,Plummer Model,Galaxies,Extragalactic Astronomy
Classifier: Development Status :: 5 - Production/Stable
Classifier: Intended Audience :: Education
Classifier: Intended Audience :: Information Technology
Classifier: Intended Audience :: Science/Research
Classifier: Topic :: Scientific/Engineering :: Astronomy
Classifier: Topic :: Software Development :: Libraries :: Python Modules
Classifier: License :: OSI Approved :: MIT License
Classifier: Programming Language :: Python :: 3.9
Classifier: Programming Language :: Python :: 3.10
Classifier: Programming Language :: Python :: 3.11
Classifier: Programming Language :: Python :: 3.12
Classifier: Programming Language :: Python :: Implementation
Classifier: Natural Language :: English
Classifier: Operating System :: Microsoft :: Windows
Classifier: Operating System :: POSIX :: Linux
Requires-Python: >=3.8
License-File: LICENSE
Requires-Dist: matplotlib >=3.7.1
Requires-Dist: numpy >=1.24.2
Requires-Dist: pandas >=2.0.0
Requires-Dist: scipy >=1.10.1
